LICENSE
README.md
setup.py
aenv/aenv.py
aenv.egg-info/PKG-INFO
aenv.egg-info/SOURCES.txt
aenv.egg-info/dependency_links.txt
aenv.egg-info/entry_points.txt
aenv.egg-info/not-zip-safe
aenv.egg-info/requires.txt
aenv.egg-info/top_level.txt