Metadata-Version: 2.1
Name: aenv
Version: 2.0.6
Summary: A Python 3 tool to fetch secure strings from the aws parameter store and injecting those into environment variables.
Home-page: https://github.com/MartinWie/AEnv
Download-URL: https://github.com/MartinWie/AEnv/archive/2.0.6.tar.gz
Author: MartinWiechmann
Author-email: martin.wiechmann.office@gmail.com
License: MIT
Keywords: aws credo security parameterstore ssm cloud password aenv
Classifier: Development Status :: 5 - Production/Stable
Classifier: Environment :: Console
Classifier: Intended Audience :: Developers
Classifier: License :: OSI Approved :: MIT License
Classifier: Programming Language :: Python :: 3
Classifier: Topic :: Security
Classifier: Operating System :: OS Independent
License-File: LICENSE
